CGenr/AST.py
CGenr/CG.py
CGenr/File.py
CGenr/__init__.py
CGenr-0.0.3.dist-info/METADATA
CGenr-0.0.3.dist-info/WHEEL
CGenr-0.0.3.dist-info/top_level.txt
CGenr-0.0.3.dist-info/RECORD
